LICENSE
MANIFEST.in
README.rst
setup.py
wagtail_readinglevel.egg-info/PKG-INFO
wagtail_readinglevel.egg-info/SOURCES.txt
wagtail_readinglevel.egg-info/dependency_links.txt
wagtail_readinglevel.egg-info/not-zip-safe
wagtail_readinglevel.egg-info/requires.txt
wagtail_readinglevel.egg-info/top_level.txt
wagtailreadinglevel/__init__.py
wagtailreadinglevel/wagtail_hooks.py
wagtailreadinglevel/static/api-monkeypatch.js
wagtailreadinglevel/static/wagtailreadinglevel.bundle.js
wagtailreadinglevelcoleman/__init__.py
wagtailreadinglevelcoleman/wagtail_hooks.py
wagtailreadinglevelflesch/__init__.py
wagtailreadinglevelflesch/wagtail_hooks.py
wagtailreadinglevelfog/__init__.py
wagtailreadinglevelfog/wagtail_hooks.py
wagtailreadinglevelsmog/__init__.py
wagtailreadinglevelsmog/wagtail_hooks.py