Metadata-Version: 1.0
Name: wagtail-readinglevel
Version: 3.5.0
Summary: Wagtail plugin that adds reading level calculations to Draftail.
Home-page: http://github.com/vixdigital/wagtail-readinglevel
Author: VIX Digital
Author-email: info@vix.digital
License: MIT
Platform: UNKNOWN
